<?xml version="1.0" encoding="utf-8"?>
<TextureAtlas imagePath="Frosty_Assets.png">
	<!-- Created with Adobe Animate version 23.0.0.407 -->
	<!-- http://www.adobe.com/products/animate.html -->
	<SubTexture name="frosty down0000" x="5" y="5" width="466" height="653"/>
	<SubTexture name="frosty down0001" x="476" y="5" width="466" height="653"/>
	<SubTexture name="frosty down0002" x="476" y="5" width="466" height="653"/>
	<SubTexture name="frosty down0003" x="947" y="5" width="466" height="653"/>
	<SubTexture name="frosty down0004" x="947" y="5" width="466" height="653"/>
	<SubTexture name="frosty down0005" x="1418" y="5" width="466" height="653"/>
	<SubTexture name="frosty down0006" x="1418" y="5" width="466" height="653"/>
	<SubTexture name="frosty down0007" x="1889" y="5" width="466" height="653"/>
	<SubTexture name="frosty down0008" x="2360" y="5" width="466" height="653"/>
	<SubTexture name="frosty down0009" x="2360" y="5" width="466" height="653"/>
	<SubTexture name="frosty down0010" x="2360" y="5" width="466" height="653"/>
	<SubTexture name="frosty down0011" x="2360" y="5" width="466" height="653"/>
	<SubTexture name="frosty down0012" x="2360" y="5" width="466" height="653"/>
	<SubTexture name="frosty down0013" x="2360" y="5" width="466" height="653"/>
	<SubTexture name="frosty idle0000" x="2831" y="5" width="413" height="647"/>
	<SubTexture name="frosty idle0001" x="2831" y="5" width="413" height="647"/>
	<SubTexture name="frosty idle0002" x="3249" y="5" width="413" height="647"/>
	<SubTexture name="frosty idle0003" x="3249" y="5" width="413" height="647"/>
	<SubTexture name="frosty idle0004" x="3667" y="5" width="413" height="647"/>
	<SubTexture name="frosty idle0005" x="3667" y="5" width="413" height="647"/>
	<SubTexture name="frosty idle0006" x="5" y="663" width="413" height="647"/>
	<SubTexture name="frosty idle0007" x="5" y="663" width="413" height="647"/>
	<SubTexture name="frosty idle0008" x="423" y="663" width="413" height="647"/>
	<SubTexture name="frosty idle0009" x="423" y="663" width="413" height="647"/>
	<SubTexture name="frosty idle0010" x="423" y="663" width="413" height="647"/>
	<SubTexture name="frosty idle0011" x="423" y="663" width="413" height="647"/>
	<SubTexture name="frosty idle0012" x="423" y="663" width="413" height="647"/>
	<SubTexture name="frosty idle0013" x="423" y="663" width="413" height="647"/>
	<SubTexture name="frosty left0000" x="841" y="663" width="502" height="682"/>
	<SubTexture name="frosty left0001" x="1348" y="663" width="502" height="682"/>
	<SubTexture name="frosty left0002" x="1348" y="663" width="502" height="682"/>
	<SubTexture name="frosty left0003" x="1855" y="663" width="502" height="682"/>
	<SubTexture name="frosty left0004" x="1855" y="663" width="502" height="682"/>
	<SubTexture name="frosty left0005" x="2362" y="663" width="502" height="682"/>
	<SubTexture name="frosty left0006" x="2362" y="663" width="502" height="682"/>
	<SubTexture name="frosty left0007" x="2869" y="663" width="502" height="682"/>
	<SubTexture name="frosty left0008" x="3376" y="663" width="502" height="682"/>
	<SubTexture name="frosty left0009" x="3376" y="663" width="502" height="682"/>
	<SubTexture name="frosty left0010" x="3376" y="663" width="502" height="682"/>
	<SubTexture name="frosty left0011" x="3376" y="663" width="502" height="682"/>
	<SubTexture name="frosty left0012" x="3376" y="663" width="502" height="682"/>
	<SubTexture name="frosty left0013" x="3376" y="663" width="502" height="682"/>
	<SubTexture name="frosty right0000" x="5" y="1350" width="495" height="655" frameX="-3" frameY="-1" frameWidth="498" frameHeight="656"/>
	<SubTexture name="frosty right0001" x="505" y="1350" width="494" height="645" frameX="-4" frameY="-11" frameWidth="498" frameHeight="656"/>
	<SubTexture name="frosty right0002" x="505" y="1350" width="494" height="645" frameX="-4" frameY="-11" frameWidth="498" frameHeight="656"/>
	<SubTexture name="frosty right0003" x="1004" y="1350" width="494" height="653" frameX="-4" frameY="-3" frameWidth="498" frameHeight="656"/>
	<SubTexture name="frosty right0004" x="1004" y="1350" width="494" height="653" frameX="-4" frameY="-3" frameWidth="498" frameHeight="656"/>
	<SubTexture name="frosty right0005" x="1503" y="1350" width="495" height="655" frameX="-3" frameY="-1" frameWidth="498" frameHeight="656"/>
	<SubTexture name="frosty right0006" x="1503" y="1350" width="495" height="655" frameX="-3" frameY="-1" frameWidth="498" frameHeight="656"/>
	<SubTexture name="frosty right0007" x="2003" y="1350" width="495" height="655" frameX="-3" frameY="-1" frameWidth="498" frameHeight="656"/>
	<SubTexture name="frosty right0008" x="2503" y="1350" width="495" height="656" frameX="-3" frameY="0" frameWidth="498" frameHeight="656"/>
	<SubTexture name="frosty right0009" x="2503" y="1350" width="495" height="656" frameX="-3" frameY="0" frameWidth="498" frameHeight="656"/>
	<SubTexture name="frosty right0010" x="2503" y="1350" width="495" height="656" frameX="-3" frameY="0" frameWidth="498" frameHeight="656"/>
	<SubTexture name="frosty right0011" x="2503" y="1350" width="495" height="656" frameX="-3" frameY="0" frameWidth="498" frameHeight="656"/>
	<SubTexture name="frosty right0012" x="2503" y="1350" width="495" height="656" frameX="-3" frameY="0" frameWidth="498" frameHeight="656"/>
	<SubTexture name="frosty right0013" x="2503" y="1350" width="495" height="656" frameX="-3" frameY="0" frameWidth="498" frameHeight="656"/>
	<SubTexture name="frosty up0000" x="3003" y="1350" width="395" height="649"/>
	<SubTexture name="frosty up0001" x="3403" y="1350" width="395" height="649"/>
	<SubTexture name="frosty up0002" x="3403" y="1350" width="395" height="649"/>
	<SubTexture name="frosty up0003" x="5" y="2011" width="395" height="649"/>
	<SubTexture name="frosty up0004" x="5" y="2011" width="395" height="649"/>
	<SubTexture name="frosty up0005" x="405" y="2011" width="395" height="649"/>
	<SubTexture name="frosty up0006" x="405" y="2011" width="395" height="649"/>
	<SubTexture name="frosty up0007" x="805" y="2011" width="395" height="649"/>
	<SubTexture name="frosty up0008" x="1205" y="2011" width="395" height="649"/>
	<SubTexture name="frosty up0009" x="1205" y="2011" width="395" height="649"/>
	<SubTexture name="frosty up0010" x="1205" y="2011" width="395" height="649"/>
	<SubTexture name="frosty up0011" x="1205" y="2011" width="395" height="649"/>
	<SubTexture name="frosty up0012" x="1205" y="2011" width="395" height="649"/>
	<SubTexture name="frosty up0013" x="1205" y="2011" width="395" height="649"/>
</TextureAtlas>
